cargo_workspace/__init__.py
cargo_workspace/dependency.py
cargo_workspace/lib.py
cargo_workspace/version.py
cargo_workspace-1.2.8.dist-info/METADATA
cargo_workspace-1.2.8.dist-info/WHEEL
cargo_workspace-1.2.8.dist-info/top_level.txt
cargo_workspace-1.2.8.dist-info/RECORD
