Metadata-Version: 2.4
Name: cargo_workspace
Version: 1.2.8
Summary: Parse a cargo workspace and analyze its packages
Author-email: Oliver Tale-Yazdi <oliver@tasty.limo>
Project-URL: Homepage, https://github.com/ggwpez/py-cargo-workspace
Keywords: cargo,rust
Classifier: Programming Language :: Python :: 3
Classifier: Operating System :: OS Independent
Classifier: License :: OSI Approved :: GNU General Public License v3 (GPLv3)
Requires-Python: >=3.6
Requires-Dist: toml>=0.10.0
Provides-Extra: test
Requires-Dist: pytest>=8.0.0; extra == "test"
